ooo_dev_cli_hlp/README.md
ooo_dev_cli_hlp/__init__.py
ooo_dev_cli_hlp/cfg/__init__.py
ooo_dev_cli_hlp/cfg/config.py
ooo_dev_cli_hlp/cli/__init__.py
ooo_dev_cli_hlp/cli/hlp.py
ooo_dev_cli_hlp/cli/interactive_hlp.py
ooo_dev_cli_hlp/config.json
ooo_dev_cli_hlp/data_class/__init__.py
ooo_dev_cli_hlp/data_class/inventory.py
ooo_dev_cli_hlp/data_class/sphinx_info.py
ooo_dev_cli_hlp/data_manage/__init__.py
ooo_dev_cli_hlp/data_manage/controller/__init__.py
ooo_dev_cli_hlp/data_manage/controller/database_controller.py
ooo_dev_cli_hlp/data_manage/db_class/__init__.py
ooo_dev_cli_hlp/data_manage/db_class/base_sql.py
ooo_dev_cli_hlp/data_manage/db_class/base_sql_table.py
ooo_dev_cli_hlp/data_manage/db_class/db_connect.py
ooo_dev_cli_hlp/data_manage/db_class/init_db.py
ooo_dev_cli_hlp/data_manage/db_class/sql_ctx.py
ooo_dev_cli_hlp/data_manage/db_class/tbl_inventory.py
ooo_dev_cli_hlp/data_manage/db_class/tbl_sphinx_info.py
ooo_dev_cli_hlp/data_manage/qry/__init__.py
ooo_dev_cli_hlp/data_manage/qry/qry_inv.py
ooo_dev_cli_hlp/res/db.sqlite3
ooo_dev_cli_hlp/web_search/__init__.py
ooo_dev_cli_hlp/web_search/browse.py
ooo_dev_odh-0.1.6.dist-info/LICENSE
ooo_dev_odh-0.1.6.dist-info/METADATA
ooo_dev_odh-0.1.6.dist-info/WHEEL
ooo_dev_odh-0.1.6.dist-info/entry_points.txt
ooo_dev_odh-0.1.6.dist-info/RECORD
