Metadata-Version: 2.1
Name: ooo-dev-odh
Version: 0.1.6
Summary: Command Line Help for my OooDev Project
Home-page: https://github.com/Amourspirit/python-ooodev-cli-hlp
License: MIT
Keywords: odev,libreoffice,openoffice,cli,ooouno
Author: :Barry-Thomas-Paul: Moss
Author-email: vibrationoflife@protonmail.com
Requires-Python: >=3.8,<4.0
Classifier: Intended Audience :: Developers
Classifier: License :: OSI Approved :: MIT License
Classifier: Operating System :: OS Independent
Classifier: Programming Language :: Python
Classifier: Programming Language :: Python :: 3
Classifier: Programming Language :: Python :: 3.8
Classifier: Programming Language :: Python :: 3.9
Classifier: Programming Language :: Python :: 3.10
Classifier: Programming Language :: Python :: 3.11
Classifier: Programming Language :: Python :: 3.12
Classifier: Topic :: Office/Business
Project-URL: Documentation, https://github.com/Amourspirit/python-ooodev-cli-hlp#readme
Project-URL: Repository, https://github.com/Amourspirit/python-ooodev-cli-hlp
